<data>
    <item type="consumable" id="burger" price="10" consumableType="FOOD">
        <name>hamburger</name>
        <effect>foodBasic</effect>
    </item>
    <item type="consumable" id="burger_cheese" price="10" consumableType="FOOD">
        <name>cheeseburger</name>
        <effect>foodBasic</effect>
    </item>
    <item type="consumable" id="burger_deluxe" price="10" consumableType="FOOD">
        <name>deluxe hamburger</name>
        <effect>foodBasic</effect>
    </item>
    <item type="consumable" id="french_fries" price="10" consumableType="FOOD">
        <name>french fries</name>
        <effect>foodBasic</effect>
    </item>
    <item type="consumable" id="nutri_chips_bacon" price="5" consumableType="FOOD">
        <name>Smoky Bacon Nutri-Chips</name>
        <effect>foodBasic</effect>
    </item>
    <item type="consumable" id="nutri_chips_wasabi" price="5" consumableType="FOOD">
        <name>Wasabi Ginger Nutri-Chips</name>
        <effect>foodBasic</effect>
    </item>
    <item type="consumable" id="gumball" price="1" consumableType="FOOD">
        <name>gumball</name>
        <effect>foodBasic</effect>
    </item>
</data>